misc_funcs_module/__init__.py
misc_funcs_module/add.py
misc_funcs_module/subtract.py
misc_funcs_module/extras/__init__.py
misc_funcs_module/extras/divide.py
misc_funcs_module/extras/multiply.py
misc_funcs_module-0.0.2.dist-info/METADATA
misc_funcs_module-0.0.2.dist-info/WHEEL
misc_funcs_module-0.0.2.dist-info/top_level.txt
misc_funcs_module-0.0.2.dist-info/RECORD
